mongopype/__init__.py
mongopype-0.0.1.dist-info/licenses/LICENSE
mongopype-0.0.1.dist-info/WHEEL
mongopype-0.0.1.dist-info/METADATA
mongopype-0.0.1.dist-info/RECORD
