Metadata-Version: 2.4
Name: mongopype
Version: 0.0.1
Summary: Pythonic builder for MongoDB aggregation pipelines
Author: Omer Cohen
Author-email: Omer Cohen <omercotkd@gmail.com>
License-Expression: MIT
License-File: LICENSE
Classifier: Programming Language :: Python :: 3
Classifier: Operating System :: OS Independent
Requires-Python: >=3.10
Project-URL: Homepage, https://github.com/omercotkd/mongopype
Project-URL: Issues, https://github.com/omercotkd/mongopype/issues
